koji_habitude/__init__.py
koji_habitude/exceptions.py
koji_habitude/intern.py
koji_habitude/koji.py
koji_habitude/loader.py
koji_habitude/namespace.py
koji_habitude/processor.py
koji_habitude/resolver.py
koji_habitude/solver.py
koji_habitude/templates.py
koji_habitude/workflow.py
koji_habitude/cli/__init__.py
koji_habitude/cli/__main__.py
koji_habitude/cli/apply.py
koji_habitude/cli/compare.py
koji_habitude/cli/diff.py
koji_habitude/cli/dump.py
koji_habitude/cli/edit.py
koji_habitude/cli/expand.py
koji_habitude/cli/fetch.py
koji_habitude/cli/templates.py
koji_habitude/cli/theme.py
koji_habitude/cli/util.py
koji_habitude/models/__init__.py
koji_habitude/models/archive_type.py
koji_habitude/models/base.py
koji_habitude/models/build_type.py
koji_habitude/models/change.py
koji_habitude/models/channel.py
koji_habitude/models/compat.py
koji_habitude/models/content_generator.py
koji_habitude/models/external_repo.py
koji_habitude/models/group.py
koji_habitude/models/host.py
koji_habitude/models/permission.py
koji_habitude/models/tag.py
koji_habitude/models/target.py
koji_habitude/models/user.py
koji_habitude-0.9.0.dist-info/licenses/LICENSE
koji_habitude-0.9.0.dist-info/METADATA
koji_habitude-0.9.0.dist-info/WHEEL
koji_habitude-0.9.0.dist-info/entry_points.txt
koji_habitude-0.9.0.dist-info/top_level.txt
koji_habitude-0.9.0.dist-info/RECORD
