Metadata-Version: 2.4
Name: koji-habitude
Version: 0.9.0
Summary: Synchronizes local koji data expectations with a hub instance
Home-page: https://github.com/obriencj/koji-habitude
Author: Christopher O'Brien
Author-email: obriencj@gmail.com
License: GNU General Public License v3
Classifier: Development Status :: 3 - Alpha
Classifier: Intended Audience :: Developers
Classifier: Programming Language :: Python :: 3
Classifier: Programming Language :: Python :: 3.9
Classifier: Programming Language :: Python :: 3.10
Classifier: Programming Language :: Python :: 3.11
Classifier: Programming Language :: Python :: 3.12
Requires-Python: >=3.9
License-File: LICENSE
Requires-Dist: click
Requires-Dist: koji
Requires-Dist: PyYAML
Requires-Dist: Jinja2
Requires-Dist: pydantic>=1.10
Provides-Extra: test
Requires-Dist: pytest; extra == "test"
Requires-Dist: pytest-cov; extra == "test"
Dynamic: license-file
